gamengine3d/__init__.py
gamengine3d/cli.py
gamengine3d/context.py
gamengine3d/engine.py
gamengine3d/game_objects.py
gamengine3d/helper.py
gamengine3d/obj_reader.py
gamengine3d/renderer.py
gamengine3d/examples/__init__.py
gamengine3d/examples/basics.py
gamengine3d/examples/from_obj.py
gamengine3d/examples/load_scene.py
gamengine3d/examples/messages_demo.py
gamengine3d/examples/player_movement.py
gamengine3d/examples/save_scene.py
gamengine3d/examples/solar_system.py
gamengine3d/examples/the_everything_demo.py
gamengine3d/examples/objects/__init__.py
gamengine3d/examples/objects/bench.obj
gamengine3d/examples/objects/crate.obj
gamengine3d/examples/objects/icosahedron.obj
gamengine3d/examples/scripts/cylinder.py
gamengine3d/examples/scripts/message_receiver.py
gamengine3d/examples/scripts/messanger_script.py
gamengine3d/examples/scripts/player_movement.py
gamengine3d/examples/scripts/settings.py
gamengine3d/examples/scripts/solar_system.py
gamengine3d/objects/0.obj
gamengine3d/objects/1.obj
gamengine3d/objects/2.obj
gamengine3d/objects/3.obj
gamengine3d/objects/4.obj
gamengine3d/objects/5.obj
gamengine3d/objects/6.obj
gamengine3d/objects/7.obj
gamengine3d/objects/8.obj
gamengine3d/objects/9.obj
gamengine3d/objects/A_capital.obj
gamengine3d/objects/B_capital.obj
gamengine3d/objects/C_capital.obj
gamengine3d/objects/D_capital.obj
gamengine3d/objects/E_capital.obj
gamengine3d/objects/F_capital.obj
gamengine3d/objects/G_capital.obj
gamengine3d/objects/H_capital.obj
gamengine3d/objects/I_capital.obj
gamengine3d/objects/J_capital.obj
gamengine3d/objects/K_capital.obj
gamengine3d/objects/L_capital.obj
gamengine3d/objects/M_capital.obj
gamengine3d/objects/N_capital.obj
gamengine3d/objects/O_capital.obj
gamengine3d/objects/P_capital.obj
gamengine3d/objects/Q_capital.obj
gamengine3d/objects/R_capital.obj
gamengine3d/objects/S_capital.obj
gamengine3d/objects/T_capital.obj
gamengine3d/objects/U_capital.obj
gamengine3d/objects/V_capital.obj
gamengine3d/objects/W_capital.obj
gamengine3d-1.21.0.dist-info/licenses/LICENSE.txt
gamengine3d-1.21.0.dist-info/METADATA
gamengine3d-1.21.0.dist-info/WHEEL
gamengine3d-1.21.0.dist-info/entry_points.txt
gamengine3d-1.21.0.dist-info/top_level.txt
gamengine3d-1.21.0.dist-info/RECORD
