Metadata-Version: 2.4
Name: gamengine3d
Version: 1.21.0
Summary: A Unity-like 3D engine in Python using pygame
Author-email: Samarth Javagal <samarthjavagal@gmail.com>
Classifier: Programming Language :: Python :: 3
Classifier: License :: OSI Approved :: MIT License
Classifier: Topic :: Games/Entertainment
Classifier: Operating System :: OS Independent
Requires-Python: >=3.8
License-File: LICENSE.txt
Requires-Dist: moderngl==5.12.0
Requires-Dist: numpy==2.3.3
Requires-Dist: pygame==2.6.1
Requires-Dist: pyrr==0.10.3
Dynamic: license-file
